setup.py
verman/__init__.py
verman/testing.py
verman.egg-info/PKG-INFO
verman.egg-info/SOURCES.txt
verman.egg-info/dependency_links.txt
verman.egg-info/top_level.txt