Metadata-Version: 1.0
Name: verman
Version: 1.1.1
Summary: verman: version management
Home-page: https://github.com/biocore/verman
Author: Daniel McDonald
Author-email: mcdonadt@colorado.edu
License: BSD
Platform: UNKNOWN
Classifier: Development Status :: 5 - Production/Stable
Classifier: License :: OSI Approved :: BSD License
Classifier: Topic :: Software Development
Classifier: Programming Language :: Python
Classifier: Programming Language :: Python :: 2.7
Classifier: Programming Language :: Python :: 3.3
Classifier: Programming Language :: Python :: Implementation :: CPython
Classifier: Operating System :: OS Independent
